podgen/__init__.py
podgen/__main__.py
podgen/category.py
podgen/compat.py
podgen/episode.py
podgen/media.py
podgen/not_supported_by_itunes_warning.py
podgen/person.py
podgen/podcast.py
podgen/util.py
podgen/version.py
podgen/warnings.py
podgen-1.1.0.dist-info/METADATA
podgen-1.1.0.dist-info/WHEEL
podgen-1.1.0.dist-info/top_level.txt
podgen-1.1.0.dist-info/RECORD
